llama_backup/__init__.py
llama_backup/cli.py
llama_backup/config.py
llama_backup/core.py
llama_backup/main.py
llama_backup/security.py
llama_backup/storage.py
llama_backup-0.1.0.dist-info/METADATA
llama_backup-0.1.0.dist-info/WHEEL
llama_backup-0.1.0.dist-info/entry_points.txt
llama_backup-0.1.0.dist-info/licenses/LICENSE
llama_backup-0.1.0.dist-info/RECORD
