Metadata-Version: 2.4
Name: llama-backup
Version: 0.1.0
Summary: Backup and restore utilities for LlamaAI data and configurations.
Project-URL: Homepage, https://github.com/yourusername/llama-backup
Project-URL: Bug Tracker, https://github.com/yourusername/llama-backup/issues
Project-URL: Documentation, https://github.com/yourusername/llama-backup/
Author-email: Your Name <your.email@example.com>
License: MIT License
License-File: LICENSE
Classifier: Development Status :: 3 - Alpha
Classifier: Intended Audience :: Developers
Classifier: Intended Audience :: System Administrators
Classifier: License :: OSI Approved :: MIT License
Classifier: Programming Language :: Python :: 3
Classifier: Programming Language :: Python :: 3.8
Classifier: Programming Language :: Python :: 3.9
Classifier: Programming Language :: Python :: 3.10
Classifier: Programming Language :: Python :: 3.11
Classifier: Topic :: Database
Classifier: Topic :: Software Development :: Libraries :: Python Modules
Classifier: Topic :: System :: Archiving :: Backup
Requires-Python: >=3.8
Requires-Dist: apscheduler>=3.10.0
Requires-Dist: loguru>=0.7.0
Requires-Dist: pydantic>=1.10.0
Requires-Dist: python-dotenv>=1.0.0
Requires-Dist: python-snappy>=0.6.0
Requires-Dist: shutil>=1.0
Requires-Dist: typer[all]>=0.9.0
Requires-Dist: zstandard>=0.19.0
Provides-Extra: all
Requires-Dist: azure-storage-blob>=12.14.0; extra == 'all'
Requires-Dist: black>=23.3.0; extra == 'all'
Requires-Dist: boto3>=1.26.0; extra == 'all'
Requires-Dist: freezegun>=1.2.0; extra == 'all'
Requires-Dist: google-cloud-storage>=2.7.0; extra == 'all'
Requires-Dist: isort>=5.12.0; extra == 'all'
Requires-Dist: mkdocs-material>=9.1.6; extra == 'all'
Requires-Dist: mkdocs>=1.4.2; extra == 'all'
Requires-Dist: mkdocstrings[python]>=0.20.0; extra == 'all'
Requires-Dist: mypy>=1.2.0; extra == 'all'
Requires-Dist: mysql-connector-python>=8.0.0; extra == 'all'
Requires-Dist: pre-commit>=3.3.1; extra == 'all'
Requires-Dist: psycopg2-binary>=2.9.0; extra == 'all'
Requires-Dist: pymongo>=4.0.0; extra == 'all'
Requires-Dist: pytest-cov>=4.1.0; extra == 'all'
Requires-Dist: pytest-mock>=3.10.0; extra == 'all'
Requires-Dist: pytest>=7.3.1; extra == 'all'
Requires-Dist: redis[hiredis]>=4.5.0; extra == 'all'
Requires-Dist: ruff>=0.0.260; extra == 'all'
Provides-Extra: aws
Requires-Dist: boto3>=1.26.0; extra == 'aws'
Provides-Extra: azure
Requires-Dist: azure-storage-blob>=12.14.0; extra == 'azure'
Provides-Extra: dev
Requires-Dist: black>=23.3.0; extra == 'dev'
Requires-Dist: freezegun>=1.2.0; extra == 'dev'
Requires-Dist: isort>=5.12.0; extra == 'dev'
Requires-Dist: mypy>=1.2.0; extra == 'dev'
Requires-Dist: pre-commit>=3.3.1; extra == 'dev'
Requires-Dist: pytest-cov>=4.1.0; extra == 'dev'
Requires-Dist: pytest-mock>=3.10.0; extra == 'dev'
Requires-Dist: pytest>=7.3.1; extra == 'dev'
Requires-Dist: ruff>=0.0.260; extra == 'dev'
Provides-Extra: docs
Requires-Dist: mkdocs-material>=9.1.6; extra == 'docs'
Requires-Dist: mkdocs>=1.4.2; extra == 'docs'
Requires-Dist: mkdocstrings[python]>=0.20.0; extra == 'docs'
Provides-Extra: gcp
Requires-Dist: google-cloud-storage>=2.7.0; extra == 'gcp'
Provides-Extra: mongo
Requires-Dist: pymongo>=4.0.0; extra == 'mongo'
Provides-Extra: mysql
Requires-Dist: mysql-connector-python>=8.0.0; extra == 'mysql'
Provides-Extra: postgres
Requires-Dist: psycopg2-binary>=2.9.0; extra == 'postgres'
Provides-Extra: redis
Requires-Dist: redis[hiredis]>=4.5.0; extra == 'redis'
